CONTROL UNIT/control_unit.sv
module control_unit (
  input[6:0] opcode,
  input[2:0] funct3,
  input[6:0] funct7,

  output ru_write,
  output[3:0] alu_op,
  output[2:0] imm_src,
  output alu_a_src,
  output alu_b_src,
  output dm_write,
  output[2:0] dm_ctrl,
  output[4:0] br_op,
  output[1:0] ru_data_src
);

  reg ru_write;
  reg[3:0] alu_op;
  reg[2:0] imm_src;
  reg alu_a_src;
  reg alu_b_src;
  reg dm_write;
  reg[2:0] dm_ctrl;
  reg[4:0] br_op;
  reg[1:0] ru_data_src;

  always @(*) begin
    case (opcode)
      7'b0110111: begin
        ru_write = 1'b1;
        alu_op = {funct7[5], funct3};
        imm_src = 3'bxxx;
        alu_a_src = 1'b0;
        alu_b_src = 1'b0;
        dm_write = 1'b0;
        dm_ctrl = 3'bxxx;
        br_op = 5'b00xxx;
        ru_data_src = 2'b00;
      end
      7'b0010011: begin
        ru_write = 1'b1;
        alu_op = {funct7[5], funct3};
        imm_src = 3'b000;
        alu_a_src = 1'b0;
        alu_b_src = 1'b1;
        dm_write = 1'b0;
        dm_ctrl = 3'bxxx;
        br_op = 5'b00xxx;
        ru_data_src = 2'b00;
      end
      7'b0010011: begin
        ru_write = 1'b1;
        alu_op = 4'b0000;
        imm_src = 3'b000;
        alu_a_src = 1'b0;
        alu_b_src = 1'b1;
        dm_write = 1'b0;
        dm_ctrl = funct3;
        br_op = 5'b00xxx;
        ru_data_src = 2'b01;
      end
    endcase
  end
  
endmodule

CONTROL UNIT/control_unit_tb.sv
`timescale 1ns / 1ps

module control_unit_tb;
  reg[6:0] opcode;
  reg[2:0] funct3;
  reg[6:0] funct7;

  wire ru_write;
  wire[3:0] alu_op;
  wire[2:0] imm_src;
  wire alu_a_src;
  wire alu_b_src;
  wire dm_write;
  wire[2:0] dm_ctrl;
  wire[4:0] br_op;
  wire[1:0] ru_data_src;

  control_unit dut(
    .opcode(opcode),
    .funct3(funct3),
    .funct7(funct7),
    .ru_write(ru_write),
    .alu_op(alu_op),
    .imm_src(imm_src),
    .alu_a_src(alu_a_src),
    .alu_b_src(alu_b_src),
    .dm_write(dm_write),
    .dm_ctrl(dm_ctrl),
    .br_op(br_op),
    .ru_data_src(ru_data_src)
  );

  initial begin
    $dumpfile("control_unit_tb.vcd"); // Nombre del archivo VCD
    $dumpvars(0, control_unit_tb); // Guardar todas las señales

    opcode = 7'b0110011; funct3 = 3'b010; funct7 = 7'b0100000; // Tipo R
    #10 opcode = 7'b0010011; funct3 = 3'b100; funct7 = 7'b0100000; // Tipo I
    #10 opcode = 7'b0000011; funct3 = 3'b101; // Tipo I Carga
    #10 opcode = 7'b1100011; funct3 = 3'b110; // Tipo B
    #10 opcode = 7'b1101111; // Tipo J
    #10 opcode = 7'b0100011; funct3 = 3'b111; // Tipo S
    #10 opcode = 7'b1100111; // Tipo I Salto
    #10 opcode = 7'b0110111; // Tipo U - lui
    #10 opcode = 7'b0010111; // Tipo U - auipc

    $finish;
  end
endmodule

CONTROL UNIT/control_unit_tb.vcd
$date
	Fri Sep 29 17:05:00 2023
$end
$version
	Icarus Verilog
$end
$timescale
	1ps
$end
$scope module control_unit_tb $end
$var wire 1 ! ru_write $end
$var wire 2 " ru_data_src [1:0] $end
$var wire 3 # imm_src [2:0] $end
$var wire 1 $ dm_write $end
$var wire 3 % dm_ctrl [2:0] $end
$var wire 5 & br_op [4:0] $end
$var wire 4 ' alu_op [3:0] $end
$var wire 1 ( alu_b_src $end
$var wire 1 ) alu_a_src $end
$var reg 3 * funct3 [2:0] $end
$var reg 7 + funct7 [6:0] $end
$var reg 7 , opcode [6:0] $end
$scope module dut $end
$var wire 3 - funct3 [2:0] $end
$var wire 7 . funct7 [6:0] $end
$var wire 7 / opcode [6:0] $end
$var reg 1 ) alu_a_src $end
$var reg 1 ( alu_b_src $end
$var reg 4 0 alu_op [3:0] $end
$var reg 5 1 br_op [4:0] $end
$var reg 3 2 dm_ctrl [2:0] $end
$var reg 1 $ dm_write $end
$var reg 3 3 imm_src [2:0] $end
$var reg 2 4 ru_data_src [1:0] $end
$var reg 1 ! ru_write $end
$upscope $end
$upscope $end
$enddefinitions $end
$comment Show the parameter values. $end
$dumpall
$end
#0
$dumpvars
b0 4
bx 3
bx 2
b0xxx 1
b1010 0
b110011 /
b100000 .
b10 -
b110011 ,
b100000 +
b10 *
0)
0(
b1010 '
b0xxx &
bx %
0$
bx #
b0 "
1!
$end
#10000
1(
b0 #
b0 3
b1100 '
b1100 0
b100 *
b100 -
b10011 ,
b10011 /
#20000
b1 "
b1 4
b101 %
b101 2
b0 '
b0 0
b101 *
b101 -
b11 ,
b11 /
#30000
bx "
bx 4
b110 &
b110 1
bx %
bx 2
1)
b101 #
b101 3
0!
b110 *
b110 -
b1100011 ,
b1100011 /
#40000
b10 "
b10 4
b1xxxx &
b1xxxx 1
b110 #
b110 3
1!
b1101111 ,
b1101111 /
#50000
bx "
bx 4
b0xxx &
b0xxx 1
b111 %
b111 2
1$
0)
b1 #
b1 3
0!
b111 *
b111 -
b100011 ,
b100011 /
#60000
b10 "
b10 4
b1xxxx &
b1xxxx 1
bx %
bx 2
0$
b0 #
b0 3
1!
b1100111 ,
b1100111 /
#70000
b0 "
b0 4
b0xxx &
b0xxx 1
x)
b10 #
b10 3
b111 '
b111 0
0!
b110111 ,
b110111 /
#80000
b10111 ,
b10111 /
