ALU/ALU.sv
module alu(
  input[31:0] operand1, // 32 bits operand
  input[31:0] operand2, // 32 biss operand
  input[2:0] func3, 
  input subsra,
  
  output[31:0] result
);
  
  wire[31:0] operand1;
  wire[31:0] operand2;
  wire[2:0] func3;
  wire subsra;
  
  reg[31:0] result;
  
  // Temporal wires
  wire[31:0] sum_result;
  wire[31:0] diff_result;
  wire[31:0] and_result;
  wire[31:0] or_result;
  wire[31:0] xor_result;
  wire[31:0] lt_result;
  wire[31:0] shl_result;
  wire[31:0] shr_result;
  wire[31:0] shra_result;
  
  assign sum_result = operand1 + operand2;
  assign diff_result = operand1 - operand2;
  assign and_result = operand1 & operand2;
  assign or_result = operand1 | operand2;
  assign xor_result = operand1 ^ operand2;
  assign lt_result = operand1 < operand2;
  assign shl_result = operand1 << operand2;
  assign shr_result = operand1 >> operand2;
  assign shra_result = operand1 >>> operand2;
  
  always @*
    begin
      case(func3)
        3'b000:
          if (subsra)
            result = diff_result;// Resta
          else
            result = sum_result; // Suma
        3'b001: //Shift Left Logical
          result = shl_result;
        3'b010: //Set Less Than
          result = lt_result;
        3'b011: //Set Less Than Unsigned
          result = lt_result;
        3'b100: //XOR
          result = xor_result;
        3'b101: 
          if (subsra) // Shift Right Arithmetic
            result = shra_result;
       	  else // Shift Right Logical
            result = shr_result;
        3'b110: // OR
          result = or_result;
        3'b111: // AND
          result = and_result;
      endcase
    end
  
endmodule

ALU/ALU_TB.sv
//TestBench para ALU.sv

module alu_tb;
  reg [31:0] operand1;
  reg [31:0] operand2;
  reg [2:0] func3;
  reg subsra;

  wire [31:0] result;

  // Instancia de la ALU
  alu dut (
    .operand1(operand1),
    .operand2(operand2),
    .func3(func3),
    .subsra(subsra),
    .result(result)
  );

  // Generación de señales de prueba
  initial begin
    $dumpfile("alu_tb.vcd"); // Nombre del archivo VCD
    $dumpvars(0, alu_tb); // Guardar todas las señales

    //Prueba #1 - Resta
    operand1 = 32;
    operand2 = 30;
    func3 = 3'b000;
    subsra = 1;

    #10; 

   //Prueba #2 - Suma
    operand1 = 32;
    operand2 = 30;
    func3 = 3'b000;
    subsra = 0;

    #10;

   //Prueba #3 - Shift Left Logical
    operand1 = 4'b0101;
    operand2 = 3;
    func3 = 3'b001;
    subsra = 0;

    #10;

    //Prueba #4 - Set Less Than
    operand1 = 32;
    operand2 = 30;
    func3 = 3'b010;
    subsra = 0;

    #10;

    //Prueba #5 - Set Less Than Unsigned
    operand1 = -32;
    operand2 = 30;
    func3 = 3'b011;
    subsra = 0;

    #10;

    //Prueba #6 - XOR
    operand1 = 32;
    operand2 = 30;
    func3 = 3'b100;
    subsra = 0;

    #10;

    //Prueba #7 - Shift Right Arithmetic
    operand1 = 32'b11000;
    operand2 = 2;
    func3 = 3'b101;
    subsra = 1;

    #10;

    //Prueba #8 - Shift Right Logical
    operand1 = 32'b11000;
    operand2 = 2;
    func3 = 3'b101;
    subsra = 0;

    #10;

    //Prueba #9 - OR
    operand1 = 1;
    operand2 = 0;
    func3 = 3'b110;
    subsra = 0;

    #10;

    //Prueba #10 - AND
    operand1 = 1;
    operand2 = 1;
    func3 = 3'b111;
    subsra = 0;

    #10;

    //Prueba #11 - Suma con overflow
    operand1 = 32'b1111_1111_1111_1111_1111_1111_1111_1111;
    operand2 = 32'b1111_1111_1111_1111_1111_1111_1111_1111;
    func3 = 3'b000;
    subsra = 0;

    #10;

    //Prueba #12 - XOR con numeros iguales
    operand1 = 745;
    operand2 = 745;
    func3 = 3'b100;
    subsra = 0;

    #10;

    //Prueba #13 - Resta con numero negativo
    operand1 = 14;
    operand2 = -6;
    func3 = 3'b000;
    subsra = 1;

    #10;

    //Prueba #14 - Shift Right Logical muy grande
    operand1 = 32'b10010;
    operand2 = 5;
    func3 = 3'b101;
    subsra = 1;
    


    // Verificación de resultados
    //$display("Suma Resultado: %b", result);

    $finish; // Finaliza la simulación
  end
endmodule

ALU/alu_tb.vcd
$date
	Fri Sep 01 18:15:46 2023
$end
$version
	Icarus Verilog
$end
$timescale
	1s
$end
$scope module alu_tb $end
$var wire 32 ! result [31:0] $end
$var reg 3 " func3 [2:0] $end
$var reg 32 # operand1 [31:0] $end
$var reg 32 $ operand2 [31:0] $end
$var reg 1 % subsra $end
$scope module dut $end
$var wire 32 & and_result [31:0] $end
$var wire 3 ' func3 [2:0] $end
$var wire 32 ( operand1 [31:0] $end
$var wire 32 ) operand2 [31:0] $end
$var wire 32 * or_result [31:0] $end
$var wire 1 % subsra $end
$var wire 32 + xor_result [31:0] $end
$var wire 32 , sum_result [31:0] $end
$var wire 32 - shra_result [31:0] $end
$var wire 32 . shr_result [31:0] $end
$var wire 32 / shl_result [31:0] $end
$var wire 32 0 lt_result [31:0] $end
$var wire 32 1 diff_result [31:0] $end
$var reg 32 2 result [31:0] $end
$upscope $end
$upscope $end
$enddefinitions $end
$comment Show the parameter values. $end
$dumpall
$end
#0
$dumpvars
b10 2
b10 1
b0 0
b0 /
b0 .
b0 -
b111110 ,
b111110 +
b111110 *
b11110 )
b100000 (
b0 '
b0 &
1%
b11110 $
b100000 #
b0 "
b10 !
$end
#10
b111110 !
b111110 2
0%
#20
b1 &
b111 *
b110 +
b101000 !
b101000 2
b1 "
b1 '
b11 $
b11 )
b1000 ,
b10 1
b0 0
b101000 /
b101 #
b101 (
#30
b0 &
b111110 *
b111110 +
b0 !
b0 2
b10 "
b10 '
b11110 $
b11110 )
b111110 ,
b10 1
b0 /
b0 .
b0 -
b100000 #
b100000 (
#40
b11111111111111111111111111111110 *
b11111111111111111111111111111110 +
b11 "
b11 '
b11111111111111111111111111111110 ,
b11111111111111111111111111000010 1
b11 .
b11 -
b11111111111111111111111111100000 #
b11111111111111111111111111100000 (
#50
b111110 *
b111110 +
b111110 !
b111110 2
b100 "
b100 '
b111110 ,
b10 1
b0 .
b0 -
b100000 #
b100000 (
#60
b11010 *
b11010 +
b110 !
b110 2
1%
b101 "
b101 '
b1100000 /
b110 .
b110 -
b10 $
b10 )
b11010 ,
b10110 1
b0 0
b11000 #
b11000 (
#70
0%
#80
b1 *
b1 +
b1 !
b1 2
b110 "
b110 '
b0 $
b0 )
b1 ,
b1 1
b0 0
b1 /
b1 .
b1 -
b1 #
b1 (
#90
b1 &
b0 +
b1 !
b1 2
b111 "
b111 '
b10 ,
b0 1
b10 /
b0 .
b0 -
b1 $
b1 )
#100
b11111111111111111111111111111111 &
b11111111111111111111111111111111 *
b11111111111111111111111111111110 !
b11111111111111111111111111111110 2
b0 "
b0 '
b11111111111111111111111111111111 $
b11111111111111111111111111111111 )
b11111111111111111111111111111110 ,
b0 1
b0 /
b0 .
b0 -
b11111111111111111111111111111111 #
b11111111111111111111111111111111 (
#110
b1011101001 &
b1011101001 *
b0 !
b0 2
b100 "
b100 '
b1011101001 $
b1011101001 )
b10111010010 ,
b0 1
b0 0
b1011101001 #
b1011101001 (
#120
b1010 &
b11111111111111111111111111111110 *
b11111111111111111111111111110100 +
b10100 !
b10100 2
1%
b0 "
b0 '
b11111111111111111111111111111010 $
b11111111111111111111111111111010 )
b1000 ,
b10100 1
b1 0
b1110 #
b1110 (
#130
b0 &
b10111 *
b10111 +
b0 !
b0 2
b101 "
b101 '
b0 0
b1001000000 /
b101 $
b101 )
b10111 ,
b1101 1
b10010 #
b10010 (
